dockwrkr/__init__.py
dockwrkr/_version.py
dockwrkr/cli.py
dockwrkr/console.py
dockwrkr/core.py
dockwrkr/docker.py
dockwrkr/exceptions.py
dockwrkr/logs.py
dockwrkr/monads.py
dockwrkr/shell.py
dockwrkr/utils.py
dockwrkr/command/__init__.py
dockwrkr/command/create.py
dockwrkr/command/exec.py
dockwrkr/command/help.py
dockwrkr/command/login.py
dockwrkr/command/pull.py
dockwrkr/command/recreate.py
dockwrkr/command/remove.py
dockwrkr/command/reset.py
dockwrkr/command/restart.py
dockwrkr/command/run.py
dockwrkr/command/start.py
dockwrkr/command/stats.py
dockwrkr/command/status.py
dockwrkr/command/stop.py
tests/__init__.py
tests/core_tests.py
dockwrkr-2.0.7.dist-info/LICENSE
dockwrkr-2.0.7.dist-info/METADATA
dockwrkr-2.0.7.dist-info/WHEEL
dockwrkr-2.0.7.dist-info/entry_points.txt
dockwrkr-2.0.7.dist-info/top_level.txt
dockwrkr-2.0.7.dist-info/RECORD
