Metadata-Version: 2.1
Name: dockwrkr
Version: 2.0.7
Summary: dockwrkr - docker container launch wrapper
Home-page: UNKNOWN
Author: Turbulent inc.
Author-email: oss@turbulent.ca
License: Apache License 2.0
Platform: UNKNOWN
Requires-Python: >=3
Requires-Dist: setuptools
Requires-Dist: PyYAML
Requires-Dist: arrow
Requires-Dist: tabulate
Requires-Dist: semver (>=2.7)
